Metadata-Version: 2.1
Name: timezone-loc
Version: 0.0.1
Summary: An application that informs you of the time in different locations and timezones
Home-page: UNKNOWN
Author: Abhilasha Jaishal
Author-email: abhilasha.jaishal@anko.com
License: UNKNOWN
Platform: UNKNOWN
Classifier: Programming Language :: Python :: 3
Classifier: License :: OSI Approved :: MIT License
Classifier: Operating System :: OS Independent
